source/__init__.py
source/block.py
source/current_portal.py
source/directory_path.py
source/file.py
source/repository.py
source/shed.py
source/shell.py
source/time_.py
source/tree.py
source/under_construction_area.py
source/user.py
shedV-0.0.0.dist-info/LICENSE
shedV-0.0.0.dist-info/METADATA
shedV-0.0.0.dist-info/WHEEL
shedV-0.0.0.dist-info/entry_points.txt
shedV-0.0.0.dist-info/top_level.txt
shedV-0.0.0.dist-info/RECORD
