Metadata-Version: 2.1
Name: shedV
Version: 0.0.0
Summary: vcs
Requires-Python: >=3.11
License-File: LICENSE
Requires-Dist: click >=8.1
